flask_slack/__init__.py
flask_slack/decorators.py
flask_slack/errors.py
flask_slack/signals.py
flask_slack/slack_manager.py
flask_slack/utils.py
Flask_Slack_Events-0.0.2.dist-info/LICENSE
Flask_Slack_Events-0.0.2.dist-info/METADATA
Flask_Slack_Events-0.0.2.dist-info/WHEEL
Flask_Slack_Events-0.0.2.dist-info/top_level.txt
Flask_Slack_Events-0.0.2.dist-info/RECORD
